{
  "name": "abacu",
  "version": "0.0.0",
  "main": "server.js",
  "dependencies": {
    "address-validator": "^0.1.4",
    "async": "^1.5.2",
    "aws-sdk": "^2.2.48",
    "base64-stream": "^0.1.3",
    "bluebird": "^3.4.1",
    "body-parser": "^1.12.4",
    "cloudant": "^1.10.0",
    "cloudant-nano":"^6.7.0",
    "crypto": "0.0.3",
    "express": "^4.12.4",
    "express-session": "^1.11.3",
    "handlebars": "^4.0.5",
    "html-pdf": "^2.2.0",
    "jsreport": "^2.8.0",
    "jsreport-phantom-pdf": "^2.5.1",
    "lodash": "^4.2.1",
    "log4js": "^0.6.38",
    "lru-cache": "^4.0.1",
    "node-schedule": "^1.2.0",
    "nodemailer": "^1.3.4",
    "paypal-rest-sdk": "^1.6.8",
    "pdfkit": "^0.7.1",
    "prerender-node": "^2.1.0",
    "sanitize-html": "^1.7.0",
    "sendgrid": "^4.0.1",
    "shortid": "^2.2.4",
    "stripe": "^3.5.0",
    "wkhtmltopdf": "^0.1.5",
    "angular": "~1.4.9",
    "json3": "~3.3.1",
    "es5-shim": "~3.1.0",
    "bootstrap": "~3.2.0",
    "angular-resource": "~1.4.9",
    "angular-cookies": "~1.4.9",
    "angular-sanitize": "~1.2.0",
    "angular-animate": "~1.4.9",
    "angular-touch": "~1.4.9",
    "angular-route": "~1.4.9",
    "file-saver": "^2.0.5",
    "angularytics": "~0.4.0",
    "lodash": "^4.5.1",
    "ng-dialog": "^0.5.8",
    "ngclipboard": "^1.1.1",
    "angular-loading-bar": "~0.9.0",
    "ng-bootstrap": "^1.6.3"
  },
  "devDependencies": {
    "autoprefixer": "^6.4.0",
    "chance": "^1.0.2",
    "each-async": "^1.1.1",
    "grunt": "^1.5.3",
    "grunt-autoprefixer": "^3.0.4",
    "grunt-concurrent": "^3.0.0",
    "grunt-contrib-clean": "^2.0.1",
    "grunt-contrib-concat": "^2.1.0",
    "grunt-contrib-connect": "^3.0.0",
    "grunt-contrib-copy": "^1.0.0",
    "grunt-contrib-cssmin": "^4.0.0",
    "grunt-contrib-htmlmin": "^3.1.0",
    "grunt-contrib-imagemin": "^4.0.0",
    "grunt-contrib-jshint": "^3.2.0",
    "grunt-contrib-uglify": "^5.2.2",
    "grunt-contrib-watch": "^1.1.0",
    "grunt-filerev": "^2.3.1",
    "grunt-google-cdn2": "^0.6.0",
    "grunt-karma": "^4.0.2",
    "grunt-newer": "^1.3.0",
    "grunt-ng-annotate": "^4.0.0",
    "grunt-svgmin": "^6.0.1",
    "grunt-usemin": "^3.1.1",
    "grunt-wiredep": "^3.0.1",
    "jasmine-core": "^2.2.0",
    "jshint-stylish": "^0.2.0",
    "karma": "^6.4.1",
    "karma-chrome-launcher": "^3.1.1",
    "karma-jasmine": "^5.1.0",
    "karma-phantomjs-launcher": "^1.0.4",
    "load-grunt-tasks": "^5.1.0",
    "postcss-cli": "^2.5.2",
    "should": "^8.3.1",
    "sinon": "^1.17.5",
    "supertest": "^1.2.0",
    "time-grunt": "^2.0.0"
  },
  "engines": {
    "node": ">=4.4.1"
  },
  "scripts": {
    "start": "node server.js",
    "test": "npm run test_backend && npm run test_frontend",
    "clean": "rm ~/temp_chair_pics/* && rm ~/generated_pdfs/*",
    "autoprefixer": "postcss -u autoprefixer -r app/styles/**/*.css",
    "test_frontend": "grunt test",
    "test_backend": "mocha tests/backend_tests/bootstrap.test.js tests/backend_tests/unit/**/*.test.js --timeout 5000"
  }
}
